{
	"1": {
		"url": "",
		"name": "",
		"type": "",
		"size": "",
		"barcode": "",
		"producer": "",
		"brand": "",
		"description": "",
		"price": ""
	},

	"2": {
		"url": "",
		"name": "",
		"type": "",
		"size": "",
		"barcode": "",
		"producer": "",
		"brand": "",
		"description": "",
		"price": ""
	},

	"3": {
		"url": "",
		"name": "",
		"type": "",
		"size": "",
		"barcode": "",
		"producer": "",
		"brand": "",
		"description": "",
		"price": ""
	},

	"4": {
		"url": "",
		"name": "",
		"type": "",
		"size": "",
		"barcode": "",
		"producer": "",
		"brand": "",
		"description": "",
		"price": ""
	},

	"5": {
		"url": "",
		"name": "",
		"type": "",
		"size": "",
		"barcode": "",
		"producer": "",
		"brand": "",
		"description": "",
		"price": ""
	},

	"6": {
		"url": "",
		"name": "",
		"type": "",
		"size": "",
		"barcode": "",
		"producer": "",
		"brand": "",
		"description": "",
		"price": ""
	},

	"7": {
		"url": "",
		"name": "",
		"type": "",
		"size": "",
		"barcode": "",
		"producer": "",
		"brand": "",
		"description": "",
		"price": ""
	},

	"8": {
		"url": "",
		"name": "",
		"type": "",
		"size": "",
		"barcode": "",
		"producer": "",
		"brand": "",
		"description": "",
		"price": ""
	},

	"9": {
		"url": "",
		"name": "",
		"type": "",
		"size": "",
		"barcode": "",
		"producer": "",
		"brand": "",
		"description": "",
		"price": ""
	},

	"10": {
		"url": "",
		"name": "",
		"type": "",
		"size": "",
		"barcode": "",
		"producer": "",
		"brand": "",
		"description": "",
		"price": ""
	},

	"11": {
		"url": "",
		"name": "",
		"type": "",
		"size": "",
		"barcode": "",
		"producer": "",
		"brand": "",
		"description": "",
		"price": ""
	},

	"12": {
		"url": "",
		"name": "",
		"type": "",
		"size": "",
		"barcode": "",
		"producer": "",
		"brand": "",
		"description": "",
		"price": ""
	},

	"13": {
		"url": "",
		"name": "",
		"type": "",
		"size": "",
		"barcode": "",
		"producer": "",
		"brand": "",
		"description": "",
		"price": ""
	},

	"14": {
		"url": "",
		"name": "",
		"type": "",
		"size": "",
		"barcode": "",
		"producer": "",
		"brand": "",
		"description": "",
		"price": ""
	},

	"15": {
		"url": "",
		"name": "",
		"type": "",
		"size": "",
		"barcode": "",
		"producer": "",
		"brand": "",
		"description": "",
		"price": ""
	},

	"16": {
		"url": "",
		"name": "",
		"type": "",
		"size": "",
		"barcode": "",
		"producer": "",
		"brand": "",
		"description": "",
		"price": ""
	},

	"17": {
		"url": "",
		"name": "",
		"type": "",
		"size": "",
		"barcode": "",
		"producer": "",
		"brand": "",
		"description": "",
		"price": ""
	}
}